{"children":[{"children":[],"uri":"https://www.notion.so/ce6c275d7d2e41e7ae838fb147a769df","type":"text","createdTime":1602011880000,"lastEditedTime":1602012360000,"title":[["My name is Maciek, I am a machine learning enthusiast and a big fan of deep learning solutions applicable in various different areas. This site consist mainly of my memos, thoughts and things I'd like to keep track of, nonetheless I hope you can find something interesting for yourself here. Happy reading!"]]},{"children":[],"uri":"https://www.notion.so/af0aec58e791404f88154c017436603b","type":"text","createdTime":1602011940000,"lastEditedTime":1602011940000,"title":[]}],"uri":"https://www.notion.so/8b4c093aae9c4601b89ad7d2718580c2","type":"page","createdTime":1601632970649,"lastEditedTime":1602064560000,"title":[["Hi there!"]],"icon":"😀","fullWidth":false,"coverPosition":1,"properties":{"'2]%":[["about"]],":H`m":[["Yes"]],"C'lP":[["Yes"]],"|Ay0":[["post"]],"title":[["Hi there!"]]}}